{
  "db_name": "PostgreSQL",
  "query": "select\n            t.id,\n            t.route_id,\n            t.direction,\n            t.assigned,\n            t.created_at,\n            array_agg(jsonb_build_object('stop_id',\n            st.stop_id,\n            'arrival',\n            st.arrival,\n            'departure',\n            st.departure)\n        order by\n            st.arrival) as stop_times\n        from\n            trips t\n        left join stop_times st on\n            t.id = st.trip_id\n        where\n            t.id = any(\n            select\n                t.id\n            from\n                trips t\n            left join stop_times st on\n                st.trip_id = t.id\n            where\n                st.arrival > now())\n        group by\n            t.id",
  "describe": {
    "columns": [
      {
        "ordinal": 0,
        "name": "id",
        "type_info": "Uuid"
      },
      {
        "ordinal": 1,
        "name": "route_id",
        "type_info": "Varchar"
      },
      {
        "ordinal": 2,
        "name": "direction",
        "type_info": "Int2"
      },
      {
        "ordinal": 3,
        "name": "assigned",
        "type_info": "Bool"
      },
      {
        "ordinal": 4,
        "name": "created_at",
        "type_info": "Timestamptz"
      },
      {
        "ordinal": 5,
        "name": "stop_times",
        "type_info": "JsonbArray"
      }
    ],
    "parameters": {
      "Left": []
    },
    "nullable": [
      false,
      false,
      false,
      false,
      false,
      null
    ]
  },
  "hash": "4a1e2e078d34e0f3b76f6ddb0a680459e48c3c80b8bbfb2c0aa2136ec167cb2d"
}
